piyush.py
piyush-0.0.1.dist-info/License
piyush-0.0.1.dist-info/METADATA
piyush-0.0.1.dist-info/WHEEL
piyush-0.0.1.dist-info/top_level.txt
piyush-0.0.1.dist-info/RECORD
