Metadata-Version: 2.1
Name: piyush
Version: 0.0.1
Summary: hi piyush
Home-page: https://github.com/phlakhani/GitUploader
Author: Piyush Lakhani
Author-email: elearning.piyush@gmail.com
License: UNKNOWN
Platform: UNKNOWN
Classifier: Programming Language :: Python :: 3
Classifier: License :: OSI Approved :: MIT License
Classifier: Operating System :: Microsoft :: Windows :: Windows 10
Classifier: Operating System :: Microsoft :: Windows :: Windows 8.1
Requires-Python: >=3.6
